gpiozero/__init__.py
gpiozero/boards.py
gpiozero/compat.py
gpiozero/devices.py
gpiozero/exc.py
gpiozero/input_devices.py
gpiozero/internal_devices.py
gpiozero/mixins.py
gpiozero/output_devices.py
gpiozero/spi_devices.py
gpiozero/threads.py
gpiozero/tones.py
gpiozero/tools.py
gpiozero/fonts/14seg.txt
gpiozero/fonts/7seg.txt
gpiozero/fonts/__init__.py
gpiozero/pins/__init__.py
gpiozero/pins/data.py
gpiozero/pins/lgpio.py
gpiozero/pins/local.py
gpiozero/pins/mock.py
gpiozero/pins/native.py
gpiozero/pins/pi.py
gpiozero/pins/pigpio.py
gpiozero/pins/rpigpio.py
gpiozero/pins/spi.py
gpiozero/pins/style.py
gpiozerocli/__init__.py
gpiozerocli/pinout.py
gpiozerocli/pintest.py
gpiozero-2.0.dist-info/LICENSE.rst
gpiozero-2.0.dist-info/METADATA
gpiozero-2.0.dist-info/WHEEL
gpiozero-2.0.dist-info/entry_points.txt
gpiozero-2.0.dist-info/top_level.txt
gpiozero-2.0.dist-info/RECORD
