Metadata-Version: 2.1
Name: gpiozero
Version: 2.0
Summary: A simple interface to GPIO devices with Raspberry Pi
Home-page: https://gpiozero.readthedocs.io/
Author: Ben Nuttall
Author-email: ben@bennuttall.com
License: BSD-3-Clause
Project-URL: Documentation, https://gpiozero.readthedocs.io/
Project-URL: Source Code, https://github.com/gpiozero/gpiozero
Project-URL: Issue Tracker, https://github.com/gpiozero/gpiozero/issues
Keywords: raspberrypi gpio
Classifier: Development Status :: 5 - Production/Stable
Classifier: Intended Audience :: Education
Classifier: Intended Audience :: Developers
Classifier: Topic :: Education
Classifier: Topic :: System :: Hardware
Classifier: License :: OSI Approved :: BSD License
Classifier: Programming Language :: Python :: 3.7
Classifier: Programming Language :: Python :: 3.8
Classifier: Programming Language :: Python :: 3.9
Classifier: Programming Language :: Python :: 3.10
Classifier: Programming Language :: Python :: 3.11
Classifier: Programming Language :: Python :: Implementation :: PyPy
Provides-Extra: test
Provides-Extra: doc
License-File: LICENSE.rst
